{
  "source": "Froedtert & Medical College of Wisconsin Cancer Network",
  "source_url": "https://www.mcw.edu/newsroom/topics/press-releases",
  "crawled_at": "2026-04-17T21:41:02.619337",
  "total_news": 1,
  "news": [
    {
      "title": "Medical College of Wisconsin Announces New President and CEO",
      "url": "https://www.mcw.edu/newsroom/news-articles/medical-college-of-wisconsin-announces-president-and-ceo",
      "date": "Apr 14, 2026",
      "type": "Press Release",
      "summary_en": "The Medical College of Wisconsin (MCW) today announced that Shekar N. Kurpad, MD, PhD, FEL ‘01, has been unanimously appointed as the institution’s seventh president and chief executive officer (CEO), effective July 1, 2026.",
      "source": "F&MCW Cancer Network",
      "category": "medical",
      "original_title": "Medical College of Wisconsin Announces New President and CEO",
      "summary_cn": "The Medical College of Wisconsin (MCW) today announced that Shekar N. Kurpad, MD, PhD, FEL ‘01, has been unanimously appointed as the institution’s seventh president and chief executive officer (CEO), effective July 1, 2026."
    }
  ],
  "translated_count": 0,
  "missing_count": 1
}