[
  {
    "title": "Purdue to offer AI and STEM professional development for Indiana educators with LEGO® Education Computer Science & AI kits",
    "url": "https://www.purdue.edu/newsroom/2026/Q2/purdue-to-offer-ai-and-stem-professional-development-for-indiana-educators-with-lego-education-computer-science-ai-kits",
    "date": "April 30, 2026",
    "type": "Purdue News",
    "summary_en": "",
    "source": "Purdue University",
    "category": "research",
    "title_cn": "Purdue to offer AI and STEM professional development for Indiana educators with LEGO® Education Computer Science & AI kits",
    "summary_cn": "",
    "translated_time": "2026-05-10T02:49:07.071386",
    "_sort_date": "2026-04-30"
  },
  {
    "title": "Purdue celebrates 13th Day of Giving",
    "url": "https://www.purdue.edu/newsroom/2026/Q2/purdue-celebrates-13th-day-of-giving",
    "date": "April 30, 2026",
    "type": "Purdue News",
    "summary_en": "",
    "source": "Purdue University",
    "category": "general",
    "title_cn": "普渡大学举办第13届捐赠日活动",
    "summary_cn": "",
    "translated_time": "2026-05-10T02:50:04.589406",
    "_sort_date": "2026-04-30"
  }
]