[
  {
    "title": "Holly Kuzmich named managing director of the Wilson Sheehan Lab for Economic Opportunities",
    "url": "https://news.nd.edu/news/holly-kuzmich-named-managing-director-of-the-wilson-sheehan-lab-for-economic-opportunities/",
    "date": "2026-04-28",
    "type": "News",
    "summary_en": "",
    "source": "Notre Dame News",
    "category": "general",
    "title_cn": "霍利·库兹米奇被任命为威尔逊·希恩经济机遇实验室常务董事",
    "summary_cn": "",
    "translated_time": "2026-05-08T12:51:06.520072",
    "_sort_date": "2026-04-28"
  },
  {
    "title": "Two Notre Dame students named US Department of State Critical Language Scholars",
    "url": "https://news.nd.edu/news/two-notre-dame-students-named-us-department-of-state-critical-language-scholars/",
    "date": "2026-04-28",
    "type": "News",
    "summary_en": "",
    "source": "Notre Dame News",
    "category": "general",
    "title_cn": "两名圣母大学学生获选为美国国务院关键语言奖学金学者",
    "summary_cn": "",
    "translated_time": "2026-05-08T12:51:42.195326",
    "_sort_date": "2026-04-28"
  },
  {
    "title": "Barbara Jatta explores art as an instrument of hope at Forum’s closing event",
    "url": "https://news.nd.edu/news/barbara-jatta-explores-art-as-an-instrument-of-hope-at-forums-closing-event/",
    "date": "2026-04-27",
    "type": "News",
    "summary_en": "",
    "source": "Notre Dame News",
    "category": "general",
    "title_cn": "芭芭拉·贾塔在论坛闭幕活动中探讨艺术作为希望的载体",
    "summary_cn": "",
    "translated_time": "2026-05-08T12:52:31.743608",
    "_sort_date": "2026-04-27"
  }
]