[
  {
    "title": "Notre Dame recognized as top producer of Gilman Scholars over program’s first 25 years",
    "url": "https://news.nd.edu/news/notre-dame-recognized-as-top-producer-of-gilman-scholars-over-programs-first-25-years/",
    "date": "2026-05-07",
    "type": "News",
    "summary_en": "",
    "source": "Notre Dame News",
    "category": "general",
    "title_cn": "吉尔曼奖学金项目设立25周年 圣母大学获评顶尖产出院校",
    "summary_cn": "",
    "translated_time": "2026-05-09T12:07:10.171245",
    "_sort_date": "2026-05-07"
  },
  {
    "title": "Martin Soros selected as valedictorian; Allison Elshoff named salutatorian for the Class of 2026",
    "url": "https://news.nd.edu/news/martin-soros-selected-as-valedictorian-allison-elshoff-named-salutatorian-for-the-class-of-2026/",
    "date": "2026-05-07",
    "type": "News",
    "summary_en": "",
    "source": "Notre Dame News",
    "category": "general",
    "title_cn": "圣母大学选定2026届毕业生最优生及次优生人选",
    "summary_cn": "",
    "translated_time": "2026-05-09T12:07:53.263218",
    "_sort_date": "2026-05-07"
  }
]