[
  {
    "title": "Urgent National Action to Save College Sports",
    "url": "https://www.whitehouse.gov/presidential-actions/2026/04/urgent-national-action-to-save-college-sports/",
    "date": "April 3, 2026",
    "category": "Presidential Actions",
    "source": "The White House",
    "title_cn": "采取全国紧急行动 挽救高校体育运动",
    "summary_cn": "",
    "translated_time": "2026-05-09T05:14:45.007269",
    "_sort_date": "2026-04-03"
  },
  {
    "title": "Liberating the Department of Homeland Security From the Democrat-Caused Shutdown",
    "url": "https://www.whitehouse.gov/presidential-actions/2026/04/liberating-the-department-of-homeland-security-from-the-democrat-caused-shutdown/",
    "date": "April 3, 2026",
    "category": "Presidential Actions",
    "source": "The White House",
    "title_cn": "将国土安全部从民主党造成的停摆中解脱出来",
    "summary_cn": "",
    "translated_time": "2026-05-09T05:15:24.783549",
    "_sort_date": "2026-04-03"
  },
  {
    "title": "Fact Sheet: President Donald J. Trump Takes Urgent National Action to Save College Sports",
    "url": "https://www.whitehouse.gov/fact-sheets/2026/04/fact-sheet-president-donald-j-trump-takes-urgent-national-action-to-save-college-sports/",
    "date": "April 3, 2026",
    "category": "Fact Sheets",
    "source": "The White House",
    "title_cn": "情况说明：唐纳德·J·特朗普总统采取全国性紧急行动拯救大学体育运动",
    "summary_cn": "",
    "translated_time": "2026-05-09T05:16:14.166770",
    "_sort_date": "2026-04-03"
  },
  {
    "title": "Strong March Jobs Report Signals Accelerating Momentum Under President Trump",
    "url": "https://www.whitehouse.gov/releases/2026/04/strong-march-jobs-report-signals-accelerating-momentum-under-president-trump/",
    "date": "April 3, 2026",
    "category": "Releases",
    "source": "The White House",
    "title_cn": "3月强劲就业报告显示特朗普总统任内动能加速提升",
    "summary_cn": "",
    "translated_time": "2026-05-09T05:16:53.305690",
    "_sort_date": "2026-04-03"
  },
  {
    "title": "Presidential Message on Easter",
    "url": "https://www.whitehouse.gov/briefings-statements/2026/04/presidential-message-on-easter/",
    "date": "April 3, 2026",
    "category": "Briefings & Statements",
    "source": "The White House",
    "title_cn": "总统复活节致辞",
    "summary_cn": "",
    "translated_time": "2026-05-09T05:17:20.858494",
    "_sort_date": "2026-04-03"
  },
  {
    "title": "First Lady Melania Trump Previews 2026 White House Easter Egg Roll Activities",
    "url": "https://www.whitehouse.gov/briefings-statements/2026/04/first-lady-melania-trump-previews-2026-white-house-easter-egg-roll-activities/",
    "date": "April 3, 2026",
    "category": "Briefings & Statements",
    "source": "The White House",
    "title_cn": "第一夫人梅拉尼娅·特朗普预览2026年白宫复活节滚彩蛋活动",
    "summary_cn": "",
    "translated_time": "2026-05-09T05:17:50.362501",
    "_sort_date": "2026-04-03"
  },
  {
    "title": "Presidential Message on the Anniversary of the Death of Pope Saint John Paul II",
    "url": "https://www.whitehouse.gov/briefings-statements/2026/04/presidential-message-on-the-anniversary-of-the-death-of-pope-saint-john-paul-ii/",
    "date": "April 2, 2026",
    "category": "Briefings & Statements",
    "source": "The White House",
    "title_cn": "总统关于教宗圣若望·保禄二世逝世周年的文告",
    "summary_cn": "",
    "translated_time": "2026-05-09T06:10:31.504531",
    "_sort_date": "2026-04-02"
  },
  {
    "title": "America is Winning Once Again a Year After Liberation Day",
    "url": "https://www.whitehouse.gov/releases/2026/04/america-is-winning-once-again-a-year-after-liberation-day/",
    "date": "April 2, 2026",
    "category": "Releases",
    "source": "The White House",
    "title_cn": "America is Winning Once Again a Year After Liberation Day",
    "summary_cn": "",
    "translated_time": "2026-05-09T06:10:58.531215",
    "_sort_date": "2026-04-02"
  },
  {
    "title": "Adjusting Imports of Pharmaceuticals and Pharmaceutical Ingredients into the United States",
    "url": "https://www.whitehouse.gov/presidential-actions/2026/04/adjusting-imports-of-pharmaceuticals-and-pharmaceutical-ingredients-into-the-united-states/",
    "date": "April 2, 2026",
    "category": "Presidential Actions",
    "source": "The White House",
    "title_cn": "美国调整药品及药用原料进口管理",
    "summary_cn": "",
    "translated_time": "2026-05-09T06:11:45.095060",
    "_sort_date": "2026-04-02"
  },
  {
    "title": "Strengthening Actions Taken to Adjust Imports of Aluminum, Steel, and Copper Into the United States",
    "url": "https://www.whitehouse.gov/presidential-actions/2026/04/strengthening-actions-taken-to-adjust-imports-of-aluminum-steel-and-copper-into-the-united-states/",
    "date": "April 2, 2026",
    "category": "Presidential Actions",
    "source": "The White House",
    "title_cn": "美国加大铝、钢铁、铜进口调整行动力度",
    "summary_cn": "",
    "translated_time": "2026-05-09T06:12:16.671607",
    "_sort_date": "2026-04-02"
  }
]