[
  {
    "title": "Augustana University Encourages Community to go ‘All in For AU’ on Giving Day 2026",
    "url": "https://www.augie.edu/news/2026/augustana-university-encourages-community-go-all-au-giving-day-2026",
    "date": "2026-05-04",
    "type": "News",
    "summary_en": "Augustana University’s 10th annual Giving Day will take place on Friday, May 15 — a 24-hour fundraising event that encourages alumni, parents, staff, faculty, coaches, administrators and friends to go “All in for AU.”",
    "source": "Augustana News",
    "category": "community",
    "title_cn": "奥古斯塔纳大学倡议社会各界在2026年捐赠日“全力支持奥大”",
    "summary_cn": "奥古斯塔纳大学近期正式发起倡议，号召所属社区各界群体参与2026年捐赠日“全力支持奥大”主题活动，共同助力学校教育事业发展。",
    "translated_time": "2026-05-08T22:15:29.877958",
    "_sort_date": "2026-05-04"
  }
]