[
  {
    "title": "Augustana University Introduces Graduating Class of 2026",
    "url": "https://www.augie.edu/news/2026/augustana-university-introduces-graduating-class-2026",
    "date": "2026-05-18",
    "type": "News",
    "summary_en": "Augustana University is proud to announce the graduating Class of 2026.",
    "source": "Augustana News",
    "category": "general",
    "title_cn": "Augustana University Introduces Graduating Class of 2026",
    "summary_cn": "",
    "_sort_date": "2026-05-18"
  }
]