[
  {
    "title": "Purdue Polytechnic faculty promotions approved by Board of Trustees",
    "url": "https://polytechnic.purdue.edu/newsroom/purdue-polytechnic-faculty-promotions-approved-board-trustees",
    "date": "2026-04-20",
    "type": "News",
    "summary_en": "",
    "source": "Purdue Polytechnic Institute",
    "category": "technology",
    "title_cn": "普渡大学董事会批准普渡理工学院12名教职人员晋升",
    "summary_cn": "",
    "translated_time": "2026-05-09T23:46:16.245903",
    "_sort_date": "2026-04-20"
  }
]