{
  "source": "Purdue University Newsroom",
  "source_url": "https://www.purdue.edu/newsroom/articles/?order=DESC&orderby=date&paged=1&custom_post_type=post",
  "crawled_at": "2026-03-30T12:24:26.845797",
  "total_news": 1,
  "news": [
    {
      "title": "普渡大学与ARCS基金会协议将全国科学学者计划扩展至印第安纳州",
      "url": "https://www.purdue.edu/newsroom/2026/Q1/purdue-arcs-foundation-agreement-expands-national-science-scholar-program-to-indiana",
      "date": "March 30, 2026",
      "type": "Purdue News",
      "summary_en": "",
      "source": "Purdue University",
      "category": "research",
      "original_title": "Purdue, ARCS Foundation agreement expands national science scholar program to Indiana",
      "summary_cn": "普渡大学与ARCS（研究成就认可）基金会达成协议，将全国科学学者计划扩展至印第安纳州。该计划将为印第安纳州的科学、工程、医学等STEM领域的研究生提供奖学金支持。ARCS基金会是一个全国性的非营利组织，致力于支持美国最优秀的研究生。通过此次合作，普渡大学的优秀研究生将有机会获得ARCS奖学金，支持他们在科学研究领域的深造。这一举措体现了普渡大学在STEM教育和研究领域的领导地位，以及其致力于培养下一代科学领袖的承诺。"
    }
  ],
  "translated_count": 1,
  "missing_count": 0
}