[
  {
    "title": "Uplifting greatness at the Celebration of Excellence",
    "url": "https://education.indiana.edu/news/2026/jan-jun/2026-04-17-celebration-of-excellence.html",
    "date": "2026-04-17",
    "type": "News",
    "summary_en": "Students, staff, and faculty gathered together this week to celebrate the year’s accomplishments and recognize the outstanding work happening across the school at the annual Celebration of Excellence.",
    "source": "IU School of Education",
    "category": "general",
    "title_cn": "印第安纳大学伯明顿分校“卓越庆典”框架下举办胡希尔科学教师协会小型研讨会",
    "summary_cn": "",
    "translated_time": "2026-05-09T16:46:46.673157",
    "_sort_date": "2026-04-17"
  },
  {
    "title": "Students receive future educator award",
    "url": "https://education.indiana.edu/news/2026/jan-jun/2026-04-16-students-receive-future-educator-award.html",
    "date": "2026-04-16",
    "type": "News",
    "summary_en": "The Indiana Association of Colleges for Teacher Education’s Outstanding Future Educator Award recognizes academic excellence and significant professional promise, demonstrated during the student teaching experience.",
    "source": "IU School of Education",
    "category": "education",
    "title_cn": "印第安纳大学伯明顿分校5名学生获2026年度杰出未来教育工作者奖项",
    "summary_cn": "",
    "translated_time": "2026-05-09T16:47:33.920397",
    "_sort_date": "2026-04-16"
  }
]