[
  {
    "title": "Alexander Gilstorf’s path was made possible by the Wayne State Guarantee",
    "url": "https://today.wayne.edu/news/2026/05/01/alexander-gilstorfs-path-was-made-possible-by-the-wayne-state-guarantee-68985",
    "date": "2026-05-01",
    "type": "News",
    "summary_en": "",
    "source": "Wayne State News",
    "category": "general",
    "title_cn": "韦恩州立大学“韦恩保障计划”为学生亚历山大·吉尔斯托夫打通求学发展路径",
    "summary_cn": "",
    "translated_time": "2026-05-09T18:55:11.148094",
    "_sort_date": "2026-05-01"
  },
  {
    "title": "Jennifer Olmsted appointed chair of James Pearson Duffy Department of Art, Art History, and Design",
    "url": "https://cfpca.wayne.edu/art/news/jennifer-olmsted-appointed-chair-of-james-pearson-duffy-department-of-art-art-history-and-design-68968",
    "date": "2026-04-30",
    "type": "News",
    "summary_en": "",
    "source": "Wayne State News",
    "category": "general",
    "title_cn": "韦恩州立大学任命珍妮弗·奥姆斯特德为詹姆斯·皮尔逊·达菲艺术、艺术史与设计系系主任",
    "summary_cn": "",
    "translated_time": "2026-05-09T18:40:25.025578",
    "_sort_date": "2026-04-30"
  }
]