[
  {
    "title": "Bridging policy and practice: Advancing gender-responsive pedagogies in Zimbabwe",
    "url": "https://www.brookings.edu/articles/faith-nkala-gender-responsive-pedagogy-zimbabwe/",
    "author": "Faith Nkala",
    "date": "April 9, 2026",
    "summary_en": "",
    "source": "Brookings Institution",
    "category": "policy",
    "title_cn": "衔接政策与实践：津巴布韦推进性别敏感教学法相关研究发布",
    "summary_cn": "",
    "translated_time": "2026-05-09T12:26:34.256651",
    "_sort_date": "2026-04-09"
  },
  {
    "title": "Skill-based education to achieve justice and sustainable livelihoods for girls and women in post-conflict northern Uganda",
    "url": "https://www.brookings.edu/articles/skills-education-girls-post-conflict-northern-uganda/",
    "author": "Betty Akullo",
    "date": "April 8, 2026",
    "summary_en": "",
    "source": "Brookings Institution",
    "category": "technology",
    "title_cn": "布鲁金斯学会发布政策简报提出 以技能本位教育助力乌干达北部冲突后地区女童与妇女实现公平权益及可持续生计",
    "summary_cn": "",
    "translated_time": "2026-05-09T12:27:16.858761",
    "_sort_date": "2026-04-08"
  }
]