{
  "source": "Indiana University News",
  "source_url": "https://news.iu.edu/news/",
  "crawled_at": "2026-04-27T12:00:37.660385",
  "total_news": 1,
  "news": [
    {
      "title": "刑事司法专家研究成果为警方处置无家可归者相关事务提供指引",
      "url": "https://news.iu.edu/college/live/news/50303-iu-criminal-justice-experts-research-offers-best-pract",
      "date": "Apr 24, 2026",
      "type": "Law and Policy",
      "summary_en": "",
      "source": "Indiana University",
      "category": "science",
      "original_title": "Criminal justice expert’s research provides police with guidance for approaching homelessness",
      "summary_cn": "2026年4月24日，美国印第安纳大学对外发布相关研究信息。\n\n本次发布的信息显示，该校刑事司法领域专家所开展的相关研究，能够为警方处置无家可归者相关事务提供专业指引。\n\n印第安纳大学为本次研究相关信息的官方发布主体，相关内容于前述日期正式公开。"
    }
  ],
  "compiled_count": 0,
  "skipped_count": 1
}