[
  {
    "title": "Indiana University and Zimmer Biomet launch research, workforce partnership",
    "url": "https://news.iu.edu/live/news/49955-indiana-university-and-zimmer-biomet-launch",
    "date": "Apr 20, 2026",
    "type": "Administration",
    "summary_en": "",
    "source": "Indiana University",
    "category": "science",
    "title_cn": "印第安纳大学与捷迈邦美启动研究及劳动力合作项目",
    "summary_cn": "",
    "translated_time": "2026-05-09T00:17:46.360126",
    "_sort_date": "2026-04-20"
  },
  {
    "title": "IU School of Optometry vision screenings improve eyesight for thousands of children and athletes",
    "url": "https://news.iu.edu/live/news/50264-iu-school-of-optometry-vision-screenings-improve",
    "date": "Apr 23, 2026",
    "type": "Health and Wellness",
    "summary_en": "",
    "source": "Indiana University",
    "category": "general",
    "title_cn": "印第安纳大学视光学院视力筛查项目改善数千名儿童与运动员视力",
    "summary_cn": "无对应需翻译的英文摘要内容",
    "translated_time": "2026-05-09T00:18:39.296881",
    "_sort_date": "2026-04-23"
  },
  {
    "title": "Students compete to design Little 500 T-shirt for IU alumnus-founded Homefield",
    "url": "https://news.iu.edu/live/news/50256-students-compete-to-design-little-500-t-shirt-for",
    "date": "Apr 20, 2026",
    "type": "Arts and Humanities",
    "summary_en": "",
    "source": "Indiana University",
    "category": "education",
    "title_cn": "学生参与印第安纳大学校友创立的Homefield品牌小500自行车赛T恤设计竞赛",
    "summary_cn": "",
    "translated_time": "2026-05-09T00:19:37.290016",
    "_sort_date": "2026-04-20"
  },
  {
    "title": "IU Public Safety offers safety tips as it prepares for busy Little 500 weekend",
    "url": "https://news.iu.edu/live/news/50253-iu-public-safety-offers-safety-tips-as-it-prepares",
    "date": "Apr 20, 2026",
    "type": "Campus Life",
    "summary_en": "",
    "source": "Indiana University",
    "category": "general",
    "title_cn": "印第安纳大学公共安全部在筹备繁忙的小500周末之际发布安全提示",
    "summary_cn": "",
    "translated_time": "2026-05-09T00:20:14.144582",
    "_sort_date": "2026-04-20"
  }
]