[
  {
    "title": "Simon appointed an editor of the Review of Economics and Statistics",
    "url": "https://oneill.indiana.edu/news/2026-0420-simon-editor-appointment.html",
    "date": "2026-04-20",
    "type": "News",
    "summary_en": "O’Neill School professor Kosali Simon is appointed editor of the Review of Economics and Statistics, helping guide top economic research and scholarly discourse.",
    "source": "O'Neill School at IU",
    "category": "general",
    "title_cn": "[待翻译] Simon appointed an editor of the Review of Economics and Statistics",
    "summary_cn": "[待翻译] ",
    "translated_time": "2026-05-07T21:53:22.862042",
    "_sort_date": "2026-04-20"
  }
]