[
  {
    "title": "Court Theatre’s ‘Out Here’ rebuilds the queer musical from the ground up",
    "url": "https://news.uchicago.edu/story/court-theatres-out-here-rebuilds-queer-musical-ground",
    "date": "2026-04-28",
    "type": "News",
    "summary_en": "Incubated at UChicago, the original work reimagines divorce, coming out at 50 and the conventions of musical theater",
    "source": "UChicago News",
    "category": "general",
    "title_cn": "考特剧院《在此处》全面重构酷儿音乐剧",
    "summary_cn": "",
    "translated_time": "2026-05-09T03:53:43.639598",
    "_sort_date": "2026-04-28"
  },
  {
    "title": "The Science Behind Seasonal Sniffles",
    "url": "https://news.uchicago.edu/science-behind-seasonal-sniffles",
    "date": "2026-04-27",
    "type": "News",
    "summary_en": "",
    "source": "UChicago News",
    "category": "general",
    "title_cn": "季节性流涕背后的科学原理",
    "summary_cn": "",
    "translated_time": "2026-05-09T03:54:11.688571",
    "_sort_date": "2026-04-27"
  },
  {
    "title": "UChicago Medicine to study impact of Formula 1 racing season on performance",
    "url": "https://news.uchicago.edu/story/uchicago-medicine-study-impact-formula-1-racing-season-performance",
    "date": "2026-04-27",
    "type": "News",
    "summary_en": "Partnership with TGR Haas F1 Team will examine physical, cognitive and psychological toll of motorsports",
    "source": "UChicago News",
    "category": "research",
    "title_cn": "芝加哥大学医学中心将研究一级方程式赛车赛季对赛场表现的影响",
    "summary_cn": "未提供对应英文原文，无法完成翻译。",
    "translated_time": "2026-05-09T03:55:00.921073",
    "_sort_date": "2026-04-27"
  },
  {
    "title": "As Chicago's sports teams angle for new deals, students offer a playbook",
    "url": "https://news.uchicago.edu/story/chicagos-sports-teams-angle-new-deals-students-offer-playbook",
    "date": "2026-04-27",
    "type": "News",
    "summary_en": "Winning team in Harris Policy Innovation Challenge at UChicago proposed sweeping overhaul of how the city handles stadium deals with pro sports franchises",
    "source": "UChicago News",
    "category": "education",
    "title_cn": "As Chicago's sports teams angle for new deals, students offer a playbook",
    "summary_cn": "",
    "translated_time": "2026-05-09T03:55:27.755614",
    "_sort_date": "2026-04-27"
  }
]