[
  {
    "title": "UChicago chemists 'film' light-matter hybrid particles",
    "url": "https://news.uchicago.edu/story/uchicago-chemists-film-light-matter-hybrid-particles",
    "date": "2026-05-01",
    "type": "News",
    "summary_en": "Breakthrough could enable future computing or electronic technologies",
    "source": "UChicago News",
    "category": "general",
    "title_cn": "[待翻译] UChicago chemists 'film' light-matter hybrid particles",
    "summary_cn": "[待翻译] ",
    "translated_time": "2026-05-07T22:23:41.665546",
    "_sort_date": "2026-05-01"
  },
  {
    "title": "At UChicago event, former U.S. officials warn Iran war is ‘unraveling’ trust in NATO",
    "url": "https://news.uchicago.edu/story/uchicago-event-former-us-officials-warn-iran-war-unraveling-trust-nato",
    "date": "2026-05-01",
    "type": "News",
    "summary_en": "Kurt Campbell and Chuck Hagel warn of a weakening of the post-World War II international order",
    "source": "UChicago News",
    "category": "general",
    "title_cn": "[待翻译] At UChicago event, former U.S. officials warn Iran war is ‘unraveling’ trust in NATO",
    "summary_cn": "[待翻译] ",
    "translated_time": "2026-05-07T22:23:42.586536",
    "_sort_date": "2026-05-01"
  },
  {
    "title": "Two UChicago scientists elected to National Academy of Sciences in 2026",
    "url": "https://news.uchicago.edu/story/two-uchicago-scientists-elected-national-academy-sciences-2026",
    "date": "2026-04-30",
    "type": "News",
    "summary_en": "",
    "source": "UChicago News",
    "category": "research",
    "title_cn": "[待翻译] Two UChicago scientists elected to National Academy of Sciences in 2026",
    "summary_cn": "[待翻译] ",
    "translated_time": "2026-05-07T22:23:11.766921",
    "_sort_date": "2026-04-30"
  },
  {
    "title": "Why the Fed matters now more than ever, with Douglas Diamond",
    "url": "https://news.uchicago.edu/big-brains-podcast-why-fed-matters-now-more-ever-douglas-diamond",
    "date": "2026-04-30",
    "type": "News",
    "summary_en": "",
    "source": "UChicago News",
    "category": "general",
    "title_cn": "[待翻译] Why the Fed matters now more than ever, with Douglas Diamond",
    "summary_cn": "[待翻译] ",
    "translated_time": "2026-05-07T22:23:12.651753",
    "_sort_date": "2026-04-30"
  },
  {
    "title": "How one researcher took on Chicago's school dropout crisis",
    "url": "https://news.uchicago.edu/story/how-one-researcher-took-chicagos-school-dropout-crisis",
    "date": "2026-04-29",
    "type": "News",
    "summary_en": "UChicago Prof. Melissa Roderick retires after 35 years of bridging research and policy to keep CPS freshmen on track to graduate",
    "source": "UChicago News",
    "category": "education",
    "title_cn": "[待翻译] How one researcher took on Chicago's school dropout crisis",
    "summary_cn": "[待翻译] ",
    "translated_time": "2026-05-07T22:23:07.388072",
    "_sort_date": "2026-04-29"
  },
  {
    "title": "Court Theatre’s ‘Out Here’ rebuilds the queer musical from the ground up",
    "url": "https://news.uchicago.edu/story/court-theatres-out-here-rebuilds-queer-musical-ground",
    "date": "2026-04-28",
    "type": "News",
    "summary_en": "Incubated at UChicago, the original work reimagines divorce, coming out at 50 and the conventions of musical theater",
    "source": "UChicago News",
    "category": "general",
    "title_cn": "[待翻译] Court Theatre’s ‘Out Here’ rebuilds the queer musical from the ground up",
    "summary_cn": "[待翻译] ",
    "translated_time": "2026-05-07T22:23:08.261964",
    "_sort_date": "2026-04-28"
  }
]