[
  {
    "title": "Convening spurs conversation, excitement about university's future",
    "url": "https://news.unl.edu/article/convening-spurs-conversation-excitement-about-universitys-future",
    "date": "2026-05-11",
    "type": "News",
    "summary_en": "",
    "source": "UNL News",
    "category": "general",
    "title_cn": "内布拉斯加大学林肯分校会议激发关于大学未来的讨论与热情",
    "summary_cn": "",
    "translated_time": "2026-05-11T12:04:01.314217",
    "_sort_date": "2026-05-11"
  },
  {
    "title": "Plant and landscape systems students take design to reality",
    "url": "https://news.unl.edu/article/plant-and-landscape-systems-students-take-design-to-reality",
    "date": "2026-05-11",
    "type": "News",
    "summary_en": "",
    "source": "UNL News",
    "category": "general",
    "title_cn": "植物与景观系统专业学生将设计转化为实践",
    "summary_cn": "近日，内布拉斯加大学林肯分校植物与景观系统300课程的学生在位于基姆大厅后方“后院农夫”园圃附近的一处隐蔽角落，经历了一场从设计图纸到现实建造的实践考验。学生们在实地施工过程中深刻认识到，良好的设计并不总能经受住现实世界的首次检验。他们跪坐于地面，将形状不规则的石板逐一调整就位，不仅是在铺设露台，更是在检验设计理念——原本在图纸上清晰而确定的构想，一旦引入地面坡度、现有植被与石材等实际因素，便呈现出完全不同的面貌。",
    "translated_time": "2026-05-11T12:04:14.617221",
    "_sort_date": "2026-05-11"
  },
  {
    "title": "Soil Judging Team takes runner-up at national contest",
    "url": "https://news.unl.edu/article/soil-judging-team-takes-runner-up-at-national-contest-0",
    "date": "2026-05-11",
    "type": "News",
    "summary_en": "",
    "source": "UNL News",
    "category": "general",
    "title_cn": "内布拉斯加大学林肯分校土壤鉴定队在全国竞赛中荣获团体亚军",
    "summary_cn": "2025年4月22日至25日，由伊利诺伊州立大学主办的北美高等院校农业教师土壤鉴定竞赛上，内布拉斯加大学林肯分校土壤鉴定队取得团体总分第二名。该队伍参加的是四年制大学组别，与来自美国各地的15所高校同台竞技。队员包括综合科学与可持续食品系统专业高年级学生阿德里安·考克斯、渔业与野生动物及环境科学专业三年级学生悉尼·霍纳克、植物与景观系统专业三年级学生普罗米斯·“PJ”·斯米尔、环境科学与植物生物学专业高年级学生安娜·纽科姆，以及环境科学专业三年级学生迭戈·桑切斯和拉拉·阿诺德。其中，考克斯在90名学生中脱颖而出，获得个人第三名。",
    "translated_time": "2026-05-11T12:04:26.135153",
    "_sort_date": "2026-05-11"
  },
  {
    "title": "29 ROTC members receive military commissions",
    "url": "https://news.unl.edu/article/29-rotc-members-receive-military-commissions-0",
    "date": "2026-05-11",
    "type": "News",
    "summary_en": "",
    "source": "UNL News",
    "category": "general",
    "title_cn": "29名预备军官训练团成员获得军事委任",
    "summary_cn": "",
    "translated_time": "2026-05-11T12:04:36.791288",
    "_sort_date": "2026-05-11"
  },
  {
    "title": "Husker graduates encouraged to lead with purpose, uplift others",
    "url": "https://news.unl.edu/article/husker-graduates-encouraged-to-lead-with-purpose-uplift-others",
    "date": "2026-05-09",
    "type": "News",
    "summary_en": "",
    "source": "UNL News",
    "category": "alumni",
    "title_cn": "内布拉斯加大学林肯分校毕业典礼鼓励毕业生以使命引领人生、助力他人成长",
    "summary_cn": "2025年5月8日至9日，内布拉斯加大学林肯分校举行毕业典礼，共授予3885个学位，创历史新高。本届毕业生共计3762人，亦为该校历届之最，生源覆盖61个国家、美国45个州及哥伦比亚特区，以及内布拉斯加州230余个社区。临时校长凯瑟琳·S·安克森在5月9日上午举行的本科生毕业典礼上表示，当下世界比以往任何时候都更需要哈斯克人，并指出毕业生是该校激励与培养改变世界的学习者、领导者及学者的活态遗产的最新成员。她强调，该校师生以超越自我的使命感引领行动，这一使命既是高等教育的承诺，也是其责任所在。",
    "translated_time": "2026-05-10T20:00:51.541977",
    "_sort_date": "2026-05-09"
  },
  {
    "title": "Bachman to cap 43-year career with a final commencement",
    "url": "https://news.unl.edu/article/bachman-to-cap-43-year-career-with-a-final-commencement",
    "date": "2026-05-08",
    "type": "News",
    "summary_en": "",
    "source": "UNL News",
    "category": "general",
    "title_cn": "内布拉斯加大学林肯分校伊娃·巴赫曼将在完成最后一届研究生毕业典礼履职后退休",
    "summary_cn": "",
    "translated_time": "2026-05-09T16:57:47.344366",
    "_sort_date": "2026-05-08"
  },
  {
    "title": "New experiences help Algahimi graduate a better engineer",
    "url": "https://news.unl.edu/article/new-experiences-help-algahimi-graduate-a-better-engineer",
    "date": "2026-05-08",
    "type": "News",
    "summary_en": "",
    "source": "UNL News",
    "category": "general",
    "title_cn": "《多元实践助力基维特学者项目学员亚当·阿尔加希米成长为更优秀工程师》",
    "summary_cn": "",
    "translated_time": "2026-05-09T16:58:22.792091",
    "_sort_date": "2026-05-08"
  },
  {
    "title": "Equestrian Team helped Velinsky gallop into career",
    "url": "https://news.unl.edu/article/equestrian-team-helped-velinsky-gallop-into-career",
    "date": "2026-05-08",
    "type": "News",
    "summary_en": "",
    "source": "UNL News",
    "category": "general",
    "title_cn": "内布拉斯加大学马术队助力毕业生伊齐·维林斯基开启马术职业生涯",
    "summary_cn": "",
    "translated_time": "2026-05-09T16:59:01.067605",
    "_sort_date": "2026-05-08"
  },
  {
    "title": "Knight takes experience building memories for Husker fans to the NHL",
    "url": "https://news.unl.edu/article/knight-takes-experience-building-memories-for-husker-fans-to-the-nhl",
    "date": "2026-05-08",
    "type": "News",
    "summary_en": "",
    "source": "UNL News",
    "category": "alumni",
    "title_cn": "内布拉斯加大学林肯分校学生乔丁·奈特凭借学习及实习经历入职国家冰球联盟佛罗里达美洲豹队",
    "summary_cn": "",
    "translated_time": "2026-05-09T16:59:39.123593",
    "_sort_date": "2026-05-08"
  },
  {
    "title": "Lankas turns multi-disciplinary drive at Nebraska into Hudl career",
    "url": "https://news.unl.edu/article/lankas-turns-multi-disciplinary-drive-at-nebraska-into-hudl-career",
    "date": "2026-05-08",
    "type": "News",
    "summary_en": "",
    "source": "UNL News",
    "category": "general",
    "title_cn": "内布拉斯加大学林肯分校毕业生莉娜·兰卡斯依托跨领域发展经历入职Hudl",
    "summary_cn": "",
    "translated_time": "2026-05-09T17:01:31.788612",
    "_sort_date": "2026-05-08"
  },
  {
    "title": "University of Nebraska–Lincoln responds to Canvas service disruption",
    "url": "https://news.unl.edu/article/university-of-nebraska-lincoln-responds-to-canvas-service-disruption",
    "date": "2026-05-08",
    "type": "News",
    "summary_en": "",
    "source": "UNL News",
    "category": "general",
    "title_cn": "内布拉斯加大学林肯分校就Canvas学习平台服务中断事宜作出回应",
    "summary_cn": "",
    "translated_time": "2026-05-09T17:02:29.535072",
    "_sort_date": "2026-05-08"
  },
  {
    "title": "Honors course brings Vietnam War lessons to new generation",
    "url": "https://news.unl.edu/article/honors-course-brings-vietnam-war-lessons-to-new-generation",
    "date": "2026-05-08",
    "type": "News",
    "summary_en": "",
    "source": "UNL News",
    "category": "general",
    "title_cn": "荣誉课程向新一代传授越南战争相关经验教训",
    "summary_cn": "",
    "translated_time": "2026-05-09T17:03:22.305975",
    "_sort_date": "2026-05-08"
  },
  {
    "title": "17 graduating students earn University Honors Program awards",
    "url": "https://news.unl.edu/article/17-graduating-students-earn-university-honors-program-awards",
    "date": "2026-05-08",
    "type": "News",
    "summary_en": "",
    "source": "UNL News",
    "category": "general",
    "title_cn": "内布拉斯加大学林肯分校17名应届毕业生获评校级荣誉项目奖项",
    "summary_cn": "",
    "translated_time": "2026-05-09T17:04:18.078276",
    "_sort_date": "2026-05-08"
  },
  {
    "title": "Transfer student support expands through institutional collaboration",
    "url": "https://news.unl.edu/article/transfer-student-support-expands-through-institutional-collaboration",
    "date": "2026-05-08",
    "type": "News",
    "summary_en": "",
    "source": "UNL News",
    "category": "general",
    "title_cn": "内布拉斯加大学林肯分校与东南社区学院深化校际合作 扩大转学学生支持服务",
    "summary_cn": "",
    "translated_time": "2026-05-09T17:05:12.322550",
    "_sort_date": "2026-05-08"
  }
]